LICENSE
README.md
setup.py
odsexport/Cell.py
odsexport/CellRange.py
odsexport/Enums.py
odsexport/Exceptions.py
odsexport/Formula.py
odsexport/ODSDocument.py
odsexport/ODSWriter.py
odsexport/Sheet.py
odsexport/Style.py
odsexport/XMLNode.py
odsexport/__init__.py
odsexport.egg-info/PKG-INFO
odsexport.egg-info/SOURCES.txt
odsexport.egg-info/dependency_links.txt
odsexport.egg-info/top_level.txt